cyclic_lamp.v
module cyclic_lamp(
    input clock,
    output reg[0:2] light   
);
parameter s0 = 0, s1 = 1, s2 =2;
parameter RED = 3'b100, GREEN = 3'b010, YELLOW = 3'b001;
reg [0:1] state;

always @ (posedge clock)
 case(state)
  s0:                // s0 means red
 begin
 state<=s1;
 end
 s1: begin            // s1 means green
 state <=s2;
 end
 s2: begin             // s2 means YELLOW
 state<=s0;
 end
 default:
 begin
 state<=s0;
 end
endcase

always @ (state)
 case(state)
 s0:                // s0 means red
 begin
 light = GREEN;
 end
 s1: begin            // s1 means green
 light = YELLOW;
 end
 s2: begin             // s2 means YELLOW
 light = RED;
 end
 default:
 begin
 light = RED;
 end
endcase
endmodule

cyclic_lamp_tb.v
module test_cyclic_lamp;
reg clk;
wire [0:2] light;
cyclic_lamp LAMP (clk, light);
always #5 clk = ~clk;
initial begin
clk = 1'b0;
#100 $finish;
end
initial begin
$dumpfile("cyclic_lamp.vcd");
$dumpvars(0,test_cyclic_lamp);
$monitor ($time, "RGY:  %b",light);
end 
endmodule

cyclic_lamp.vcd
$date
	Thu May 15 14:42:34 2025
$end
$version
	Icarus Verilog
$end
$timescale
	1s
$end
$scope module test_cyclic_lamp $end
$var wire 3 ! light [0:2] $end
$var reg 1 " clk $end
$scope module LAMP $end
$var wire 1 " clock $end
$var parameter 3 # GREEN $end
$var parameter 3 $ RED $end
$var parameter 3 % YELLOW $end
$var parameter 32 & s0 $end
$var parameter 32 ' s1 $end
$var parameter 32 ( s2 $end
$var reg 3 ) light [0:2] $end
$var reg 2 * state [0:1] $end
$upscope $end
$upscope $end
$enddefinitions $end
$comment Show the parameter values. $end
$dumpall
b10 (
b1 '
b0 &
b1 %
b100 $
b10 #
$end
#0
$dumpvars
bx *
bx )
0"
bx !
$end
#5
b10 !
b10 )
b0 *
1"
#10
0"
#15
b1 !
b1 )
b1 *
1"
#20
0"
#25
b100 !
b100 )
b10 *
1"
#30
0"
#35
b10 !
b10 )
b0 *
1"
#40
0"
#45
b1 !
b1 )
b1 *
1"
#50
0"
#55
b100 !
b100 )
b10 *
1"
#60
0"
#65
b10 !
b10 )
b0 *
1"
#70
0"
#75
b1 !
b1 )
b1 *
1"
#80
0"
#85
b100 !
b100 )
b10 *
1"
#90
0"
#95
b10 !
b10 )
b0 *
1"
