Adders/half_adder.v
module half_adder(a,b,s,cout);
input a,b;
output s, cout;

//assign s = a^b;
//assign cout = a&b;

xor G1 (s,a,b);
and G2 (cout,a,b);

endmodule

Adders/full_adder.v
module full_adder(x,y,cin,sum,carry);
input x,y,cin;
output sum,carry;

wire w1,w2,w3;
half_adder HA1(.a(x),
            .b(y),
            .s(w1),
            .cout(w2));

half_adder HA2(.a(w1),
            .b(cin),
            .s(sum),
            .cout(w3));

or or1 (carry,w3,w2);

endmodule

Adders/full_adder_tb.v
`timescale 1ns/1ns
module full_adder_tb;
reg a,b,cin;
wire sum, carry;

integer i;

full_adder DUT(a,b,cin,sum,carry);

initial
begin
a = 1'b0;
b = 1'b0;
cin = 1'b0;
end
initial 
 begin
 $dumpfile("full_adder_tb.vcd");
 $dumpvars(0,full_adder_tb);
for (i=0;i<8;i=i+1)
begin
{a,b,cin}=i;
#10;
end 
end
initial
$monitor("Input a=%b, b=%b, c=%b, output sum=%b, carry=%b",a,b,cin,sum,carry);
initial #100 $finish;

endmodule

Adders/full_adder_tb.vcd
$date
	Sun Mar 23 13:29:20 2025
$end
$version
	Icarus Verilog
$end
$timescale
	1ns
$end
$scope module full_adder_tb $end
$var wire 1 ! sum $end
$var wire 1 " carry $end
$var reg 1 # a $end
$var reg 1 $ b $end
$var reg 1 % cin $end
$var integer 32 & i [31:0] $end
$scope module DUT $end
$var wire 1 " carry $end
$var wire 1 % cin $end
$var wire 1 # x $end
$var wire 1 $ y $end
$var wire 1 ' w3 $end
$var wire 1 ( w2 $end
$var wire 1 ) w1 $end
$var wire 1 ! sum $end
$scope module HA1 $end
$var wire 1 # a $end
$var wire 1 $ b $end
$var wire 1 ( cout $end
$var wire 1 ) s $end
$upscope $end
$scope module HA2 $end
$var wire 1 ) a $end
$var wire 1 % b $end
$var wire 1 ' cout $end
$var wire 1 ! s $end
$upscope $end
$upscope $end
$upscope $end
$enddefinitions $end
$comment Show the parameter values. $end
$dumpall
$end
#0
$dumpvars
0)
0(
0'
b0 &
0%
0$
0#
0"
0!
$end
#10
1!
1%
b1 &
#20
1)
1!
1$
0%
b10 &
#30
1"
0!
1'
1%
b11 &
#40
0"
1!
0'
1#
0$
0%
b100 &
#50
1"
0!
1'
1%
b101 &
#60
0)
1(
0!
0'
1$
0%
b110 &
#70
1!
1%
b111 &
#80
b1000 &
