counter/counter.v
module counter(
    input wire clk,
    input wire reset,
    output reg[3:0] cout
);

always @(posedge clk or posedge reset)begin
    if(reset) begin
        cout<= 4'b0000;
    end else begin
        cout<=cout+1;
    end
end

endmodule

counter/counter_tb.v
`timescale 1ns/1ps
module counter_tb;

// declare signals
reg clk;
reg reset;
wire [3:0]cout;

//instantiate the counter module 
counter uut (
    .clk(clk),
    .reset(reset),
    .cout(cout)
);

//generate clock signals

initial begin
    clk =0;
    forever #5 clk =~clk;
end

//Test sequence
initial begin
 $dumpfile("counter_tb.vcd");
 $dumpvars(0,counter_tb);
reset =1;
#10;

reset =0;
#100;

reset =1;
#50;
$finish;

end

endmodule

counter/counter_tb.vcd
$date
	Sat Jun 22 23:14:03 2024
$end
$version
	Icarus Verilog
$end
$timescale
	1ps
$end
$scope module counter_tb $end
$var wire 4 ! cout [3:0] $end
$var reg 1 " clk $end
$var reg 1 # reset $end
$scope module uut $end
$var wire 1 " clk $end
$var wire 1 # reset $end
$var reg 4 $ cout [3:0] $end
$upscope $end
$upscope $end
$enddefinitions $end
$comment Show the parameter values. $end
$dumpall
$end
#0
$dumpvars
b0 $
1#
0"
b0 !
$end
#5000
1"
#10000
0"
0#
#15000
b1 !
b1 $
1"
#20000
0"
#25000
b10 !
b10 $
1"
#30000
0"
#35000
b11 !
b11 $
1"
#40000
0"
#45000
b100 !
b100 $
1"
#50000
0"
#55000
b101 !
b101 $
1"
#60000
0"
#65000
b110 !
b110 $
1"
#70000
0"
#75000
b111 !
b111 $
1"
#80000
0"
#85000
b1000 !
b1000 $
1"
#90000
0"
#95000
b1001 !
b1001 $
1"
#100000
0"
#105000
b1010 !
b1010 $
1"
#110000
b0 !
b0 $
0"
1#
