multiplybyaddition/controller.v
// control path controls data flow through FSM
// start with S0 with everything reset, S1 is loading of multiplicand in A
// S2 is initializing P with 0 and B with multiplier
// S3 sets P = Z(intermediate sum of A with P), and decrement B, checks if B==0
// S4 is final state
// assuming B is non zero
module controller(
    output reg LdA,
    output reg LdB,
    output reg LdP,
    output reg clrP,
    output reg decB,
    output reg done,
    input clk,
    input eqz,
    input start
);
reg [2:0] state;
parameter S0=3'b000, S1=3'b001, S2=3'b010, S3=3'b011, S4=3'b100;

always @(posedge clk)
    begin
    case(state)
        S0: if(start) state<=S1;
        S1: state<=S2;
        S2: state<=S3;
        S3: #2 if(eqz) state<=S4;
        S4: state<=S4;
        default: state<=S0;
    endcase
   end
//next state logic
always @(state)
   begin
    case(state)
        S0: begin 
             #1 LdA=0; LdB=0; LdP=0;
                clrP=0; decB=0;
            end
        S1: begin
             #1 LdA=1; 
            end
        S2: begin
             #1 LdA =0; LdB=1; clrP=1;
            end
        S3: begin
             #1 LdB=0; LdP=1; clrP=0; decB=1;
            end
        S4: begin
             #1 done=1;
              LdB=0; LdP=0; decB=0;
            end
        default: begin
              #1 LdA=0; LdB=0; LdP=0;
                clrP=0;decB=0;
            end
    endcase
end
endmodule

multiplybyaddition/equaltoz.v
module EQZ(
    output eqz,
    input [15:0] data
);
assign eqz = (data==0);
endmodule

multiplybyaddition/add.v
module ADD(
    output reg[15:0] out,
    input [15:0] in1,
    input [15:0] in2
);
always @(*)
 out = in1+in2;
endmodule

multiplybyaddition/counter.v
// initializing B with multiplier and decrementing
module CNTR(
    output reg[15:0] dout,
    input [15:0] din,
    input ld,
    input dec,
    input clk
);
always @(posedge clk)
  if(ld) dout<=din;
  else if (dec) dout<=dout-1;
endmodule

multiplybyaddition/pipo2.v
// initializing register P to 0 if clear, otherwise loading with intermediate sum results
module PIPO2(
    output reg[15:0] dout,
    input [15:0] din,
    input ld,
    input clr,
    input clk
);
always @(posedge clk)
   if(clr) dout<=16'b0;
   else if (ld) dout<=din;
endmodule

multiplybyaddition/pipo1.v
// initializing register A with multiplicand
module PIPO1(
    output reg[15:0] dout,
    input [15:0] din,
    input ld,
    input clk
);
always @(posedge clk)
    if(ld) dout<=din;
endmodule

multiplybyaddition/multiply_datapath.v
//datapath has datacomputing components as registers, alu
`include "add.v"
`include "counter.v"
`include "equaltoz.v"
`include "pipo1.v"
`include "pipo2.v"

module Multiply_datapath(
    output eqz,
    input LdA,
    input LdB,
    input LdP,
    input clrP,
    input decB,
    input clk,
    input [15:0] data_in    
);

wire [15:0] X,Y,Z, Bout, Bus;
assign Bus = data_in;

PIPO1 A (X,Bus,LdA,clk); // initializing X = A
PIPO2 P (Y,Z,LdP, clrP,clk); // P = 0, then sum results of Z
CNTR B (Bout,Bus,LdB,decB,clk); //  Bout = B, then -1 while looping in State3
ADD AD (Z,X,Y);
EQZ COMP (eqz,Bout);

endmodule

multiplybyaddition/multiply_tb.v
module Multiply_test;
reg [15:0] data_in;
reg clk,start;
wire done;

Multiply_datapath DP(eqz,LdA,LdB,LdP,clrP,decB,clk,data_in);
controller CON(LdA,LdB,LdP,clrP,decB,done,clk,eqz,start);

initial 
 begin
 clk=1'b0;
 #3 start = 1'b1;
 #500 $finish;
end

always #5 clk =~clk;

initial begin
 #17 data_in = 16'd17;
 #10 data_in = 16'd5 ;
end

initial begin
 $monitor($time," %d %b ",DP.Y,done);
 $dumpfile("mul.vcd");
 $dumpvars(0,Multiply_test);
end
endmodule

multiplybyaddition/mul.vcd
$date
	Tue Jul 01 23:08:05 2025
$end
$version
	Icarus Verilog
$end
$timescale
	1s
$end
$scope module Multiply_test $end
$var wire 1 ! eqz $end
$var wire 1 " done $end
$var wire 1 # decB $end
$var wire 1 $ clrP $end
$var wire 1 % LdP $end
$var wire 1 & LdB $end
$var wire 1 ' LdA $end
$var reg 1 ( clk $end
$var reg 16 ) data_in [15:0] $end
$var reg 1 * start $end
$scope module CON $end
$var wire 1 ( clk $end
$var wire 1 * start $end
$var wire 1 ! eqz $end
$var parameter 3 + S0 $end
$var parameter 3 , S1 $end
$var parameter 3 - S2 $end
$var parameter 3 . S3 $end
$var parameter 3 / S4 $end
$var reg 1 ' LdA $end
$var reg 1 & LdB $end
$var reg 1 % LdP $end
$var reg 1 $ clrP $end
$var reg 1 # decB $end
$var reg 1 " done $end
$var reg 3 0 state [2:0] $end
$upscope $end
$scope module DP $end
$var wire 16 1 Bus [15:0] $end
$var wire 1 ' LdA $end
$var wire 1 & LdB $end
$var wire 1 % LdP $end
$var wire 1 ( clk $end
$var wire 1 $ clrP $end
$var wire 16 2 data_in [15:0] $end
$var wire 1 # decB $end
$var wire 1 ! eqz $end
$var wire 16 3 Z [15:0] $end
$var wire 16 4 Y [15:0] $end
$var wire 16 5 X [15:0] $end
$var wire 16 6 Bout [15:0] $end
$scope module A $end
$var wire 1 ( clk $end
$var wire 16 7 din [15:0] $end
$var wire 1 ' ld $end
$var reg 16 8 dout [15:0] $end
$upscope $end
$scope module AD $end
$var wire 16 9 in1 [15:0] $end
$var wire 16 : in2 [15:0] $end
$var reg 16 ; out [15:0] $end
$upscope $end
$scope module B $end
$var wire 1 ( clk $end
$var wire 1 # dec $end
$var wire 16 < din [15:0] $end
$var wire 1 & ld $end
$var reg 16 = dout [15:0] $end
$upscope $end
$scope module COMP $end
$var wire 16 > data [15:0] $end
$var wire 1 ! eqz $end
$upscope $end
$scope module P $end
$var wire 1 ( clk $end
$var wire 1 $ clr $end
$var wire 16 ? din [15:0] $end
$var wire 1 % ld $end
$var reg 16 @ dout [15:0] $end
$upscope $end
$upscope $end
$upscope $end
$enddefinitions $end
$comment Show the parameter values. $end
$dumpall
b100 /
b11 .
b10 -
b1 ,
b0 +
$end
#0
$dumpvars
bx @
bx ?
bx >
bx =
bx <
bx ;
bx :
bx 9
bx 8
bx 7
bx 6
bx 5
bx 4
bx 3
bx 2
bx 1
bx 0
x*
bx )
0(
x'
x&
x%
x$
x#
x"
x!
$end
#3
1*
#5
b0 0
1(
#6
0#
0$
0%
0&
0'
#10
0(
#15
b1 0
1(
#16
1'
#17
b10001 1
b10001 7
b10001 <
b10001 )
b10001 2
#20
0(
#25
b10001 5
b10001 8
b10001 9
b10 0
1(
#26
1$
1&
0'
#27
b101 1
b101 7
b101 <
b101 )
b101 2
#30
0(
#35
b10001 3
b10001 ;
b10001 ?
b11 0
0!
b101 6
b101 =
b101 >
b0 4
b0 :
b0 @
1(
#36
1#
0$
1%
0&
#40
0(
#45
b100010 3
b100010 ;
b100010 ?
b10001 4
b10001 :
b10001 @
b100 6
b100 =
b100 >
1(
#50
0(
#55
b110011 3
b110011 ;
b110011 ?
b11 6
b11 =
b11 >
b100010 4
b100010 :
b100010 @
1(
#60
0(
#65
b1000100 3
b1000100 ;
b1000100 ?
b110011 4
b110011 :
b110011 @
b10 6
b10 =
b10 >
1(
#70
0(
#75
b1010101 3
b1010101 ;
b1010101 ?
b1 6
b1 =
b1 >
b1000100 4
b1000100 :
b1000100 @
1(
#80
0(
#85
b1100110 3
b1100110 ;
b1100110 ?
b1010101 4
b1010101 :
b1010101 @
1!
b0 6
b0 =
b0 >
1(
#87
b100 0
#88
0#
0%
1"
