DFF_/dffasyn.v
// d flip flop with asynchronous set and reset
module dffasyn(
    input d,
    input clk,
    input reset,
    input set,
    output reg q,
    output qbar
);
assign qbar = ~q;
//considers neg trigger of reset and set
always @(posedge clk or negedge reset or negedge set) 
begin
if (reset==0) q<=0;
else if (set==0) q<=1;
else q<=d;
end

endmodule

DFF_/dff_tb.v
module dff_test;
reg clk, reset,set,d;
wire qbar,q;

//dff dut (d,clk,reset,set,q,qbar);
dffasyn dut (d,clk,reset,set,q,qbar);

initial begin
clk=1'b0;
 d=1'b0;
 reset =1'b1;
 set = 1'b1;
forever 
#5 clk = ~clk;
end

initial begin
$dumpfile("dff_tb.vcd");
$dumpvars(0,dff_test);

#3 d=1'b1;
#6 reset =1'b0;
#10 reset=1'b1; set = 1'b0;d=1'b0;
#10 set = 1'b1;
#5 d=1'b1;
end

initial #50 $finish;

endmodule

DFF_/dff_tb.vcd
$date
	Mon Mar 31 22:05:17 2025
$end
$version
	Icarus Verilog
$end
$timescale
	1s
$end
$scope module dff_test $end
$var wire 1 ! qbar $end
$var wire 1 " q $end
$var reg 1 # clk $end
$var reg 1 $ d $end
$var reg 1 % reset $end
$var reg 1 & set $end
$scope module dut $end
$var wire 1 # clk $end
$var wire 1 $ d $end
$var wire 1 ! qbar $end
$var wire 1 % reset $end
$var wire 1 & set $end
$var reg 1 " q $end
$upscope $end
$upscope $end
$enddefinitions $end
$comment Show the parameter values. $end
$dumpall
$end
#0
$dumpvars
1&
1%
0$
0#
x"
x!
$end
#3
1$
#5
0!
1"
1#
#9
1!
0"
0%
#10
0#
#15
1#
#19
0!
1"
0$
0&
1%
#20
0#
#25
1#
#29
1&
#30
0#
#35
1!
0"
1#
#40
0#
#45
1#
#48
1$
